{
  "project_info": {
    "project_number": "681508618650",
    "project_id": "assetmanagement-9d7e1",
    "storage_bucket": "assetmanagement-9d7e1.appspot.com"
  },
  "client": [
    {
      "client_info": {
        "mobilesdk_app_id": "1:681508618650:android:f38f6f7e8ea508d7e9ba23",
        "android_client_info": {
          "package_name": "com.example.as"
        }
      },
      "oauth_client": [],
      "api_key": [
        {
          "current_key": "AIzaSyABykFxK_AgoRzI-Bvy9fgXq0UKFStZbEM"
        }
      ],
      "services": {
        "appinvite_service": {
          "other_platform_oauth_client": []
        }
      }
    },
    {
      "client_info": {
        "mobilesdk_app_id": "1:681508618650:android:2fd3fdbcee6d249ee9ba23",
        "android_client_info": {
          "package_name": "com.example.asset_management"
        }
      },
      "oauth_client": [],
      "api_key": [
        {
          "current_key": "AIzaSyABykFxK_AgoRzI-Bvy9fgXq0UKFStZbEM"
        }
      ],
      "services": {
        "appinvite_service": {
          "other_platform_oauth_client": []
        }
      }
    }
  ],
  "configuration_version": "1"
}